<?xml version="1.0" encoding="UTF-8"?>
<window>
	<defaultcontrol always="true">9110</defaultcontrol>
	<allowoverlay>no</allowoverlay>
	<onload>CancelAlarm(StartupCheck,true)</onload>
	<onload>AlarmClock(StartupComplete,SetProperty(StartupComplete,true,Home),00:05,silent)</onload>
	<onload>RunScript(script.skinshortcuts,type=buildxml&amp;mainmenuID=9110&amp;group=mainmenu|submenu|pvrwidgets|widgets1|widgets2|widgets3|widgets4|widgets5|widgets6|widgets7|widgets8|widgets9|widgets10)</onload>
	<controls>
		<control type="group">
			<include>transition_Home</include>
			<include>home_Background</include>
			<include>home_NowPlaying</include>
			<control type="image">
				<include>screen_Dimensions</include>
				<texture background="true" colordiffuse="base_1play">overlays/base_color.png</texture>
				<visible>!Player.HasMedia + !Player.HasAudio</visible>
				<include>fadeinout</include>
			</control>
			<!--widgets-->
			<include>widget_container</include>
			<include>widgetspanel</include>
			<include>hub</include>
			<include>home_weather</include>
			<include>home_PVRrecwidget</include>
			<!--clock-->
			<control type="group">
				<visible>Skin.HasSetting(home.time) + ![Control.HasFocus(91411) | Control.HasFocus(91412) | Control.HasFocus(91413) | Control.HasFocus(91511) | Control.HasFocus(91512) | Control.HasFocus(91513) | Window.IsActive(infodialog) | Window.IsActive(extendedprogressdialog)]</visible>
				<include>clock</include>
				<include>fadeinout</include>
			</control>
			<!--rss-->
			<control type="rss" id="1">
				<top>690</top>
				<width>1280</width>			  
				<font>font12</font>
				<textcolor>Color3</textcolor>
				<headlinecolor>Color3</headlinecolor>
				<titlecolor>Color2</titlecolor>
				<include>fadeinout</include>
				<visible>[[Control.HasFocus(9110) | Control.HasFocus(9901) | Control.HasFocus(918111) | Control.HasFocus(91611) | Control.HasFocus(91612) | Control.HasFocus(91613)] + Skin.HasSetting(home.menu2)] | [[Control.HasFocus(9110) | Control.HasFocus(918111) | Control.HasFocus(91611) | Control.HasFocus(91612) | Control.HasFocus(91613)] + !Skin.HasSetting(home.menu2)]</visible>			  
			</control>			
			<!--Menu new-->
			<control type="group">
				<posx>0</posx>
				<posy>30</posy>
				<animation tween="Back" easing="InOut" effect="slide" end="0,400" time="1000" condition="ControlGroup(91401).HasFocus() | ControlGroup(91402).HasFocus() | ControlGroup(91403).HasFocus() | ControlGroup(91501).HasFocus() | ControlGroup(91502).HasFocus() | ControlGroup(91503).HasFocus()">Conditional</animation>
				<animation tween="Back" easing="InOut" effect="slide" start="0,250" end="0,0" time="1000" condition="!ControlGroup(91401).HasFocus() + !ControlGroup(91402).HasFocus() + !ControlGroup(91403).HasFocus() + !ControlGroup(91501).HasFocus() + !ControlGroup(91502).HasFocus() + !ControlGroup(91503).HasFocus()">Conditional</animation>
				<animation tween="Back" easing="InOut" effect="slide" start="0,250" end="0,0" time="1000">WindowOpen</animation>
				<animation tween="Back" easing="InOut" effect="slide" start="0,-720" end="0,0" time="1000" condition="!ControlGroup(5562).HasFocus() + !ControlGroup(5563).HasFocus() + !ControlGroup(5564).HasFocus() + !ControlGroup(5565).HasFocus()">Conditional</animation>
				<animation tween="Back" easing="InOut" effect="slide" start="0,0" end="0,-720" time="500" delay="500" condition="ControlGroup(5562).HasFocus() | ControlGroup(5563).HasFocus() | ControlGroup(5564).HasFocus() | ControlGroup(5565).HasFocus()">Conditional</animation>
				<animation tween="Back" easing="InOut" effect="slide" end="0,-30" time="300" condition="ControlGroup(9901).HasFocus + !Skin.HasSetting(home.menu2)">Conditional</animation>
				<control type="image">
					<width>1280</width>
					<height>100</height>
					<posy>460</posy>
					<texture background="true" colordiffuse="base_1play">overlays/diffuse.png</texture>
					<visible>Skin.HasSetting(home.menu2)</visible>
				</control>
				<control type="image">
					<width>1280</width>
					<height>141</height>
					<posy>460</posy>
					<texture background="true" colordiffuse="whitetrans">overlays/cover_overlay.png</texture>
					<visible>Skin.HasSetting(home.menu2)</visible>
				</control>
				<control type="wraplist" id="9110">
					<posy>327</posy>
					<width>1500</width>
					<animation effect="slide" start="0,0" end="-50,0" time="0" condition="!Skin.HasSetting(home.menu2)">Conditional</animation>
					
					<onup condition="Control.IsVisible(91401) + !IsEmpty(Container(9110).ListItem.Property(widget))">SetFocus(91411,0)</onup>
					<onup condition="Control.IsVisible(91501) + !IsEmpty(Container(9110).ListItem.Property(widget))">SetFocus(91511,0)</onup>
					<onup condition="Control.IsVisible(91601) + !IsEmpty(Container(9110).ListItem.Property(widget))">SetFocus(91611,0)</onup>
					<onup condition="Control.IsVisible(91402) + !IsEmpty(Container(9110).ListItem.Property(widget))">SetFocus(91412,0)</onup>
					<onup condition="Control.IsVisible(91502) + !IsEmpty(Container(9110).ListItem.Property(widget))">SetFocus(91512,0)</onup>
					<onup condition="Control.IsVisible(91602) + !IsEmpty(Container(9110).ListItem.Property(widget))">SetFocus(91612,0)</onup>
					<onup condition="Control.IsVisible(91403) + !IsEmpty(Container(9110).ListItem.Property(widget))">SetFocus(91413,0)</onup>
					<onup condition="Control.IsVisible(91503) + !IsEmpty(Container(9110).ListItem.Property(widget))">SetFocus(91513,0)</onup>
					<onup condition="Control.IsVisible(91603) + !IsEmpty(Container(9110).ListItem.Property(widget))">SetFocus(91613,0)</onup><onup condition="Control.IsVisible(9186) + !IsEmpty(Container(9110).ListItem.Property(widget))">SetFocus(918111,0)</onup>				
					<ondown condition="Control.IsVisible(9901) + IntegerGreaterThan(Container(9901).NumItems,0)">SetFocus(9901)</ondown>
					<orientation>horizontal</orientation>
					<include condition="Skin.HasSetting(home.menu2)">homepos2</include>
					<include condition="!Skin.HasSetting(home.menu2)">homepos1</include>
					<content><include>skinshortcuts-mainmenu</include></content>
					<itemlayout width="320" height="150" condition="Skin.HasSetting(home.menu2)">
						<control type="group">
							<posx>0</posx>
							<posy>130</posy>
							<control type="label">
								<align>center</align>
								<height>100</height>
								<font>light_Category</font>
								<selectedcolor>green</selectedcolor>
								<info>ListItem.Label</info>
							</control>
						</control>
					</itemlayout>
					<focusedlayout height="150" width="350" condition="Skin.HasSetting(home.menu2)">
						<control type="group">
							<posx>0</posx>
							<posy>130</posy>
							<control type="label">
								<align>center</align>
								<aligny>center</aligny>
								<height>100</height>
								<font>light_Header_Big</font>
								<selectedcolor>green</selectedcolor>
								<info>ListItem.Label</info>
								<visible>Control.HasFocus(9110)</visible>
							</control>
							<control type="label">
								<align>center</align>
								<aligny>center</aligny>
								<height>100</height>
								<font>light_Header</font>
								<selectedcolor>green</selectedcolor>
								<info>ListItem.Label</info>
								<visible>!Control.HasFocus(9110)</visible>
							</control>
						</control>
					</focusedlayout>
					<itemlayout width="250" height="150" condition="!Skin.HasSetting(home.menu2)">
						<control type="group">
							<posx>0</posx>
							<posy>130</posy>
							<control type="label">
								<align>center</align>
								<height>100</height>
								<font>light_Header</font>
								<selectedcolor>green</selectedcolor>
								<info>ListItem.Label</info>
							</control>
						</control>
					</itemlayout>
					<focusedlayout height="300" width="455" condition="!Skin.HasSetting(home.menu2)">
						<control type="group">
							<top>5</top>
							<control type="image">
								<posx>-118</posx>
								<posy>40</posy>
								<width>488</width>
								<height>275</height>
								<texture>frames/frame-alt.png</texture>
								<animation effect="fade" start="0" end="100" time="100" delay="400">Conditional</animation>
								<aspectratio>stretch</aspectratio>
							</control>
							<control type="image">
								<posx>-100</posx>
								<posy>50</posy>
								<width>450</width>
								<height>255</height>
								<texture>white.png</texture>
								<include>bordertrans</include>
								<visible>Control.HasFocus(9110)</visible>
								<aspectratio>scale</aspectratio>
							</control>
							<control type="image">
								<posx>-100</posx>
								<posy>50</posy>
								<width>450</width>
								<height>255</height>
								<info>ListItem.Icon</info>
								<fadetime>500</fadetime>
								<include>bordertrans_Big</include>
								<aspectratio>scale</aspectratio>
							</control>
							<control type="image">
								<posx>-100</posx>
								<posy>50</posy>
								<width>450</width>
								<height>255</height>
								<texture background="true">overlays/cover_overlay.png</texture>
								<visible>!Skin.HasSetting(globalGlass.disable)</visible>
							</control>
						</control>
						<control type="group">
							<top>5</top>
							<control type="label">
								<posx>-100</posx>
								<posy>5</posy>
								<width>450</width>
								<height>22</height>
								<font>light_Header</font>
								<aligny>center</aligny>
								<textcolor>Color1</textcolor>
								<selectedcolor>base_3</selectedcolor>
								<align>left</align>
								<info>ListItem.Label</info>
							</control>
						</control>
					</focusedlayout>
				</control>
				<include>home_subm</include>
			</control>
		</control>
		
		<control type="image">
			<top>screen_Height</top>
			<include>screen_Dimensions</include>
			<texture background="true">special://skin/fanart.jpg</texture>
			<animation type="WindowOpen" condition="Window.Previous(startup)" reversible="false">
				<effect type="slide" time="500" start="0,-720" end="0,0" tween="Cubic" easing="InOut" center="screen_Center" delay="0" />
			</animation>
			<visible>Window.Previous(startup)</visible>
		</control>
	</controls>
</window>